README.md
setup.cfg
setup.py
ply_pybasic.egg-info/PKG-INFO
ply_pybasic.egg-info/SOURCES.txt
ply_pybasic.egg-info/dependency_links.txt
ply_pybasic.egg-info/requires.txt
ply_pybasic.egg-info/top_level.txt
pybasic/__init__.py
pybasic/__main__.py
pybasic/basic_ast.py
pybasic/basic_lex.py
pybasic/basic_lib.py
pybasic/basic_operators.py
pybasic/basic_types.py
pybasic/basic_yacc.py
pybasic/parsetab.py
pybasic/pybasic.py
pybasic/symbol_table.py
pybasic/utils.py