Metadata-Version: 1.1
Name: ply-pybasic
Version: 1.0
Summary: UNKNOWN
Home-page: https://github.com/Hou-Rui/pybasic
Author: Hou Rui
Author-email: 13244639785@163.com
License: UNKNOWN
Keywords: ply python BASIC interpreter
Platform: UNKNOWN
Classifier: Development Status :: 4 - Beta
Classifier: Programming Language :: Python :: 3
Classifier: Topic :: Software Development :: Interpreters
